{
  "batch_number": 10,
  "batch_size": 10,
  "files": {
    "통화 녹음 신기연_251110_222457.m4a": {
      "file": "통화 녹음 신기연_251110_222457.m4a",
      "file_path": "/home/innojini/dev/voice.man/ref/call/통화 녹음 신기연_251110_222457.m4a",
      "file_size_mb": 8.580777168273926,
      "modified_time": "2026-01-08T07:48:46.274422",
      "duration_seconds": 555.3706875,
      "sample_rate": 16000,
      "samples": 8885931,
      "forensic_features": {
        "f0_mean": 185.8003104465093,
        "f0_std": 57.76396373612622,
        "f0_min": 50.0,
        "f0_max": 527.8031643091576,
        "voiced_ratio": 0.7656141968195437,
        "mfcc_mean": -25.745346069335938,
        "mfcc_std": 103.22384643554688,
        "spectral_centroid": 1675.909856431059,
        "zcr_mean": 0.22834001705101983,
        "rms_mean": 0.06659547239542007,
        "rms_std": 0.06657303124666214,
        "spectral_rolloff": 3096.1568585791656,
        "chroma_mean": 0.36015284061431885,
        "tempo": 117.1875
      },
      "analysis_timestamp": "2026-01-10T18:34:45.304597",
      "status": "✅ SUCCESS",
      "warnings": "⚠️ 메모리 부족: 91.1%\n⚠️ CPU 온도 높음: 82.8°C"
    },
    "통화 녹음 신기연_251111_154731.m4a": {
      "file": "통화 녹음 신기연_251111_154731.m4a",
      "file_path": "/home/innojini/dev/voice.man/ref/call/통화 녹음 신기연_251111_154731.m4a",
      "file_size_mb": 3.4865217208862305,
      "modified_time": "2026-01-08T07:48:46.285423",
      "duration_seconds": 222.165375,
      "sample_rate": 16000,
      "samples": 3554646,
      "forensic_features": {
        "f0_mean": 181.89084627858838,
        "f0_std": 70.65665890790727,
        "f0_min": 50.28964705339267,
        "f0_max": 501.06577544965126,
        "voiced_ratio": 0.7521244418839118,
        "mfcc_mean": -23.512746810913086,
        "mfcc_std": 101.16606903076172,
        "spectral_centroid": 1602.2315301183085,
        "zcr_mean": 0.2186168707466153,
        "rms_mean": 0.05605282261967659,
        "rms_std": 0.05557020753622055,
        "spectral_rolloff": 2935.269786115512,
        "chroma_mean": 0.36142513155937195,
        "tempo": 117.1875
      },
      "analysis_timestamp": "2026-01-10T18:34:57.074956",
      "status": "✅ SUCCESS",
      "warnings": "⚠️ 메모리 부족: 91.0%\n⚠️ CPU 온도 높음: 82.7°C"
    },
    "통화 녹음 신기연_251118_190150.m4a": {
      "file": "통화 녹음 신기연_251118_190150.m4a",
      "file_path": "/home/innojini/dev/voice.man/ref/call/통화 녹음 신기연_251118_190150.m4a",
      "file_size_mb": 13.94205379486084,
      "modified_time": "2026-01-08T07:48:46.326427",
      "duration_seconds": 902.4,
      "sample_rate": 16000,
      "samples": 14438400,
      "forensic_features": {
        "f0_mean": 182.25838227159647,
        "f0_std": 72.1003009448439,
        "f0_min": 50.0,
        "f0_max": 512.7776327682916,
        "voiced_ratio": 0.7985177830573383,
        "mfcc_mean": -22.223560333251953,
        "mfcc_std": 92.30960845947266,
        "spectral_centroid": 1514.185662671643,
        "zcr_mean": 0.1700015555188646,
        "rms_mean": 0.06887830793857574,
        "rms_std": 0.05732804164290428,
        "spectral_rolloff": 2731.3479021134003,
        "chroma_mean": 0.3321674168109894,
        "tempo": 125.0
      },
      "analysis_timestamp": "2026-01-10T18:35:40.904527",
      "status": "✅ SUCCESS",
      "warnings": "⚠️ 메모리 부족: 91.2%\n⚠️ CPU 온도 높음: 82.6°C"
    },
    "통화 녹음 신기연_251124_091622.m4a": {
      "file": "통화 녹음 신기연_251124_091622.m4a",
      "file_path": "/home/innojini/dev/voice.man/ref/call/통화 녹음 신기연_251124_091622.m4a",
      "file_size_mb": 0.6316518783569336,
      "modified_time": "2026-01-08T07:48:46.328428",
      "duration_seconds": 40.832,
      "sample_rate": 16000,
      "samples": 653312,
      "forensic_features": {
        "f0_mean": 184.0674406354048,
        "f0_std": 79.68250084428075,
        "f0_min": 50.0,
        "f0_max": 423.78523774371814,
        "voiced_ratio": 0.7094753328112764,
        "mfcc_mean": -27.843305587768555,
        "mfcc_std": 111.32501983642578,
        "spectral_centroid": 1500.8618673355584,
        "zcr_mean": 0.2048571175117463,
        "rms_mean": 0.038847774267196655,
        "rms_std": 0.040308866649866104,
        "spectral_rolloff": 2822.2090348472984,
        "chroma_mean": 0.3699701130390167,
        "tempo": 98.6842105263158
      },
      "analysis_timestamp": "2026-01-10T18:35:43.997655",
      "status": "✅ SUCCESS",
      "warnings": "⚠️ 메모리 부족: 91.1%\n⚠️ CPU 온도 높음: 83.0°C"
    },
    "통화 녹음 신기연_251124_111614.m4a": {
      "file": "통화 녹음 신기연_251124_111614.m4a",
      "file_path": "/home/innojini/dev/voice.man/ref/call/통화 녹음 신기연_251124_111614.m4a",
      "file_size_mb": 1.2924575805664062,
      "modified_time": "2026-01-08T07:48:46.332428",
      "duration_seconds": 83.605375,
      "sample_rate": 16000,
      "samples": 1337686,
      "forensic_features": {
        "f0_mean": 170.04453014331213,
        "f0_std": 67.84274869584782,
        "f0_min": 50.0,
        "f0_max": 524.7632417749795,
        "voiced_ratio": 0.7715269804822044,
        "mfcc_mean": -25.310014724731445,
        "mfcc_std": 110.68392944335938,
        "spectral_centroid": 1734.3977621357496,
        "zcr_mean": 0.24535712363662457,
        "rms_mean": 0.048592403531074524,
        "rms_std": 0.044844530522823334,
        "spectral_rolloff": 3258.048698813624,
        "chroma_mean": 0.38579556345939636,
        "tempo": 125.0
      },
      "analysis_timestamp": "2026-01-10T18:35:48.882050",
      "status": "✅ SUCCESS",
      "warnings": "⚠️ 메모리 부족: 91.1%\n⚠️ CPU 온도 높음: 82.5°C"
    },
    "통화 녹음 신기연_251124_121946.m4a": {
      "file": "통화 녹음 신기연_251124_121946.m4a",
      "file_path": "/home/innojini/dev/voice.man/ref/call/통화 녹음 신기연_251124_121946.m4a",
      "file_size_mb": 0.31952667236328125,
      "modified_time": "2026-01-08T07:48:46.333428",
      "duration_seconds": 20.629375,
      "sample_rate": 16000,
      "samples": 330070,
      "forensic_features": {
        "f0_mean": 236.99552078328466,
        "f0_std": 89.13513002278988,
        "f0_min": 50.28964705339267,
        "f0_max": 521.7408279062257,
        "voiced_ratio": 0.8186046511627907,
        "mfcc_mean": -23.93083953857422,
        "mfcc_std": 99.0571517944336,
        "spectral_centroid": 1713.7357488035102,
        "zcr_mean": 0.1835498425387597,
        "rms_mean": 0.056967031210660934,
        "rms_std": 0.04449772834777832,
        "spectral_rolloff": 3221.3178294573645,
        "chroma_mean": 0.3205418884754181,
        "tempo": 144.23076923076923
      },
      "analysis_timestamp": "2026-01-10T18:35:51.055209",
      "status": "✅ SUCCESS",
      "warnings": "⚠️ 메모리 부족: 91.0%\n⚠️ CPU 온도 높음: 81.5°C"
    },
    "통화 녹음 신기연_251125_095244.m4a": {
      "file": "통화 녹음 신기연_251125_095244.m4a",
      "file_path": "/home/innojini/dev/voice.man/ref/call/통화 녹음 신기연_251125_095244.m4a",
      "file_size_mb": 0.577265739440918,
      "modified_time": "2026-01-08T07:48:46.334428",
      "duration_seconds": 37.312,
      "sample_rate": 16000,
      "samples": 596992,
      "forensic_features": {
        "f0_mean": 221.76927787575977,
        "f0_std": 87.20523578872971,
        "f0_min": 50.0,
        "f0_max": 537.0290011121053,
        "voiced_ratio": 0.779777206512425,
        "mfcc_mean": -21.41770362854004,
        "mfcc_std": 90.00440979003906,
        "spectral_centroid": 1692.9004913912356,
        "zcr_mean": 0.20381662716902313,
        "rms_mean": 0.08591929823160172,
        "rms_std": 0.07590990513563156,
        "spectral_rolloff": 3111.490467009426,
        "chroma_mean": 0.34292829036712646,
        "tempo": 117.1875
      },
      "analysis_timestamp": "2026-01-10T18:35:53.828629",
      "status": "✅ SUCCESS",
      "warnings": "⚠️ 메모리 부족: 91.0%\n⚠️ CPU 온도 높음: 81.1°C"
    },
    "통화 녹음 신동식(3D개발자)_250521_132228.m4a": {
      "file": "통화 녹음 신동식(3D개발자)_250521_132228.m4a",
      "file_path": "/home/innojini/dev/voice.man/ref/call/통화 녹음 신동식(3D개발자)_250521_132228.m4a",
      "file_size_mb": 54.36611461639404,
      "modified_time": "2026-01-08T07:48:46.530449",
      "duration_seconds": 3492.48,
      "sample_rate": 16000,
      "samples": 55879680,
      "forensic_features": {
        "f0_mean": 127.86164112296701,
        "f0_std": 30.772909466874427,
        "f0_min": 50.0,
        "f0_max": 459.47934199881405,
        "voiced_ratio": 0.7444040278172273,
        "mfcc_mean": -20.899616241455078,
        "mfcc_std": 97.04291534423828,
        "spectral_centroid": 1546.6800303925618,
        "zcr_mean": 0.204218115428093,
        "rms_mean": 0.06170887500047684,
        "rms_std": 0.0491868332028389,
        "spectral_rolloff": 3007.1197321584004,
        "chroma_mean": 0.38198375701904297,
        "tempo": 125.0
      },
      "analysis_timestamp": "2026-01-10T18:38:41.272473",
      "status": "✅ SUCCESS",
      "warnings": "⚠️ 메모리 부족: 91.7%\n⚠️ CPU 온도 높음: 81.3°C"
    },
    "통화 녹음 신동식(3D개발자)_250522_102804.m4a": {
      "file": "통화 녹음 신동식(3D개발자)_250522_102804.m4a",
      "file_path": "/home/innojini/dev/voice.man/ref/call/통화 녹음 신동식(3D개발자)_250522_102804.m4a",
      "file_size_mb": 0.1642313003540039,
      "modified_time": "2026-01-08T07:48:46.532449",
      "duration_seconds": 10.581375,
      "sample_rate": 16000,
      "samples": 169302,
      "forensic_features": {
        "f0_mean": 170.0642592323403,
        "f0_std": 39.5601372125231,
        "f0_min": 98.2820598545251,
        "f0_max": 257.8740616879158,
        "voiced_ratio": 0.5891238670694864,
        "mfcc_mean": -17.228845596313477,
        "mfcc_std": 68.86662292480469,
        "spectral_centroid": 1883.769679258477,
        "zcr_mean": 0.17551276907099697,
        "rms_mean": 0.11866094917058945,
        "rms_std": 0.0938715934753418,
        "spectral_rolloff": 3424.612915407855,
        "chroma_mean": 0.3691438138484955,
        "tempo": 117.1875
      },
      "analysis_timestamp": "2026-01-10T18:38:42.936045",
      "status": "✅ SUCCESS",
      "warnings": "⚠️ 메모리 부족: 91.2%\n⚠️ CPU 온도 높음: 81.4°C"
    },
    "통화 녹음 신동식(3D개발자)_250523_081819.m4a": {
      "file": "통화 녹음 신동식(3D개발자)_250523_081819.m4a",
      "file_path": "/home/innojini/dev/voice.man/ref/call/통화 녹음 신동식(3D개발자)_250523_081819.m4a",
      "file_size_mb": 33.72598361968994,
      "modified_time": "2026-01-08T07:48:46.654462",
      "duration_seconds": 2182.997375,
      "sample_rate": 16000,
      "samples": 34927958,
      "forensic_features": {
        "f0_mean": 132.52211156129113,
        "f0_std": 33.24865505181897,
        "f0_min": 50.0,
        "f0_max": 537.0290011121053,
        "voiced_ratio": 0.7638927571497677,
        "mfcc_mean": -20.752193450927734,
        "mfcc_std": 94.6920394897461,
        "spectral_centroid": 1498.704767431671,
        "zcr_mean": 0.18494029367963838,
        "rms_mean": 0.06871011108160019,
        "rms_std": 0.052387088537216187,
        "spectral_rolloff": 2892.4814980064207,
        "chroma_mean": 0.357271283864975,
        "tempo": 125.0
      },
      "analysis_timestamp": "2026-01-10T18:40:31.577906",
      "status": "✅ SUCCESS",
      "warnings": "⚠️ 메모리 부족: 91.1%\n⚠️ CPU 온도 높음: 82.0°C"
    }
  },
  "batch_metrics": {
    "total_processing_time": 374.7577097415924,
    "average_time_per_file": 37.47577097415924,
    "successful_files": 10,
    "failed_files": 0,
    "success_rate": 100.0
  },
  "performance_data": [
    {
      "timestamp": "2026-01-10T18:34:45.304611",
      "cpu_percent": 41.3,
      "memory": 91.1,
      "disk": 66.4,
      "gpu_memory": 0.0,
      "gpu_utilization": 0.0,
      "cpu_temperature": 82.8,
      "gpu_temperature": 59.0,
      "file_processing_time": 28.46285605430603
    },
    {
      "timestamp": "2026-01-10T18:34:57.074968",
      "cpu_percent": 43.4,
      "memory": 91.0,
      "disk": 66.4,
      "gpu_memory": 0.0,
      "gpu_utilization": 0.0,
      "cpu_temperature": 82.7,
      "gpu_temperature": 59.0,
      "file_processing_time": 11.770101308822632
    },
    {
      "timestamp": "2026-01-10T18:35:40.910870",
      "cpu_percent": 40.5,
      "memory": 91.2,
      "disk": 66.4,
      "gpu_memory": 0.0,
      "gpu_utilization": 0.0,
      "cpu_temperature": 82.6,
      "gpu_temperature": 58.0,
      "file_processing_time": 43.836437940597534
    },
    {
      "timestamp": "2026-01-10T18:35:43.997677",
      "cpu_percent": 43.7,
      "memory": 91.1,
      "disk": 66.4,
      "gpu_memory": 0.0,
      "gpu_utilization": 0.0,
      "cpu_temperature": 83.0,
      "gpu_temperature": 58.0,
      "file_processing_time": 3.0865135192871094
    },
    {
      "timestamp": "2026-01-10T18:35:48.882062",
      "cpu_percent": 43.0,
      "memory": 91.1,
      "disk": 66.4,
      "gpu_memory": 0.0,
      "gpu_utilization": 0.0,
      "cpu_temperature": 82.5,
      "gpu_temperature": 58.0,
      "file_processing_time": 4.875875949859619
    },
    {
      "timestamp": "2026-01-10T18:35:51.055225",
      "cpu_percent": 44.2,
      "memory": 91.0,
      "disk": 66.4,
      "gpu_memory": 0.0,
      "gpu_utilization": 0.0,
      "cpu_temperature": 81.5,
      "gpu_temperature": 58.0,
      "file_processing_time": 2.173165798187256
    },
    {
      "timestamp": "2026-01-10T18:35:53.828640",
      "cpu_percent": 43.8,
      "memory": 91.0,
      "disk": 66.4,
      "gpu_memory": 0.0,
      "gpu_utilization": 0.0,
      "cpu_temperature": 81.1,
      "gpu_temperature": 58.0,
      "file_processing_time": 2.773684501647949
    },
    {
      "timestamp": "2026-01-10T18:38:41.272486",
      "cpu_percent": 40.6,
      "memory": 91.7,
      "disk": 66.4,
      "gpu_memory": 0.0,
      "gpu_utilization": 0.0,
      "cpu_temperature": 81.3,
      "gpu_temperature": 58.0,
      "file_processing_time": 167.44282364845276
    },
    {
      "timestamp": "2026-01-10T18:38:42.936057",
      "cpu_percent": 45.0,
      "memory": 91.2,
      "disk": 66.4,
      "gpu_memory": 0.0,
      "gpu_utilization": 0.0,
      "cpu_temperature": 81.4,
      "gpu_temperature": 58.0,
      "file_processing_time": 1.6620595455169678
    },
    {
      "timestamp": "2026-01-10T18:40:31.599310",
      "cpu_percent": 40.0,
      "memory": 91.1,
      "disk": 66.4,
      "gpu_memory": 0.0,
      "gpu_utilization": 0.0,
      "cpu_temperature": 82.0,
      "gpu_temperature": 59.0,
      "file_processing_time": 108.6631326675415
    }
  ]
}